examples/__init__.py
examples/chain_from_automl.py
examples/chain_log.py
examples/chain_tune.py
examples/forecasting_model_composing.py
examples/multiclass_prediction.py
examples/time_series_forecasting.py
examples/tpot_vs_fedot.py
examples/utils.py
examples/test/__init__.py
examples/test/test_examples.py
fedot/__init__.py
fedot/core/__init__.py
fedot/core/chain_validation.py
fedot/core/log.py
fedot/core/utils.py
fedot/core/algorithms/__init__.py
fedot/core/algorithms/time_series/__init__.py
fedot/core/algorithms/time_series/lagged_features.py
fedot/core/algorithms/time_series/prediction.py
fedot/core/algorithms/time_series/scale.py
fedot/core/composer/__init__.py
fedot/core/composer/chain.py
fedot/core/composer/chain_tune.py
fedot/core/composer/composer.py
fedot/core/composer/constraint.py
fedot/core/composer/metrics.py
fedot/core/composer/node.py
fedot/core/composer/random_composer.py
fedot/core/composer/timer.py
fedot/core/composer/ts_chain.py
fedot/core/composer/visualisation.py
fedot/core/composer/write_history.py
fedot/core/composer/gp_composer/__init__.py
fedot/core/composer/gp_composer/fixed_structure_composer.py
fedot/core/composer/gp_composer/gp_composer.py
fedot/core/composer/optimisers/__init__.py
fedot/core/composer/optimisers/crossover.py
fedot/core/composer/optimisers/gp_operators.py
fedot/core/composer/optimisers/gp_optimiser.py
fedot/core/composer/optimisers/inheritance.py
fedot/core/composer/optimisers/mutation.py
fedot/core/composer/optimisers/regularization.py
fedot/core/composer/optimisers/selection.py
fedot/core/debug/__init__.py
fedot/core/debug/metrics.py
fedot/core/models/__init__.py
fedot/core/models/data.py
fedot/core/models/model.py
fedot/core/models/preprocessing.py
fedot/core/models/transformation.py
fedot/core/models/evaluation/__init__.py
fedot/core/models/evaluation/automl_eval.py
fedot/core/models/evaluation/data_evaluation.py
fedot/core/models/evaluation/evaluation.py
fedot/core/models/evaluation/keras_eval.py
fedot_example_test-0.0.4.dist-info/LICENSE.md
fedot_example_test-0.0.4.dist-info/METADATA
fedot_example_test-0.0.4.dist-info/WHEEL
fedot_example_test-0.0.4.dist-info/top_level.txt
fedot_example_test-0.0.4.dist-info/RECORD
