Metadata-Version: 2.1
Name: fedot-example-test
Version: 0.0.4
Summary: Evolutionary structural learning framework FEDOT
Home-page: https://github.com/nccr-itmo/FEDOT
Author: pv
Author-email: pv@example.com
License: BSD 3-Clause
Platform: UNKNOWN
Classifier: License :: OSI Approved :: MIT License
Classifier: Programming Language :: Python :: 3.6
Classifier: Programming Language :: Python :: 3.7
Classifier: Programming Language :: Python :: 3.8
Requires-Python: >=3.6
Requires-Dist: scikit-optimize (==0.7.4)
Requires-Dist: pandas (==1.1.0)
Requires-Dist: statsmodels (==0.12.0)
Requires-Dist: ete3 (==3.1.1)
Requires-Dist: numpy (==1.18.0)
Requires-Dist: pytest (==5.2.0)
Requires-Dist: anytree (==2.8.0)
Requires-Dist: typing (==3.7.4.1)
Requires-Dist: scikit-learn (==0.22.1)
Requires-Dist: matplotlib (==3.0.2)
Requires-Dist: networkx (==2.4)
Requires-Dist: xgboost (==1.0.1)
Requires-Dist: Pillow (==7.1.0)
Requires-Dist: imageio (==2.8.0)
Requires-Dist: pydot (==1.4.1)
Requires-Dist: hyperopt (==0.2.4)
Requires-Dist: joblib (==0.17.0)
Requires-Dist: dataclasses (==0.7) ; python_version < "3.7"
Requires-Dist: seaborn (==0.9.0) ; python_version < "3.7"
Requires-Dist: tensorflow (==2.1.0) ; python_version <= "3.7"
Requires-Dist: tensorflow (==2.3.1) ; python_version == "3.8"
